[{"line":5,"elements":[{"start_timestamp":"2022-05-25T12:30:31.497Z","before":[{"result":{"duration":7840000000,"status":"passed"},"match":{"location":"factory.ApplicationHooks.launchBrowser()"}}],"line":76,"name":"Check progressbar-text functionality working or not","description":"","id":"feature-to-learning-automation-test-functionality;check-progressbar-text-functionality-working-or-not","after":[{"result":{"duration":97000000,"status":"passed"},"match":{"location":"factory.ApplicationHooks.quitBrowser()"}}],"type":"scenario","keyword":"Scenario","steps":[{"result":{"duration":2501000000,"status":"passed"},"line":77,"name":"user is on Home Page","match":{"location":"StepDefinition.RegisterSteps.user_is_on_home_page()"},"after":[{"result":{"duration":4000000,"status":"passed"},"match":{"location":"factory.ApplicationHooks.tearDown(io.cucumber.java.Scenario)"}}],"keyword":"Given "},{"result":{"duration":9689000000,"status":"passed"},"line":78,"name":"user click on downloadprogressbarlink","match":{"location":"StepDefinition.Learning_steps.user_click_on_downloadprogressbarlink()"},"after":[{"result":{"duration":1000000,"status":"passed"},"match":{"location":"factory.ApplicationHooks.tearDown(io.cucumber.java.Scenario)"}}],"keyword":"When "},{"result":{"duration":9598000000,"status":"passed"},"line":79,"name":"Verify progressbar for filedownload","match":{"location":"StepDefinition.Learning_steps.Verify_progressbar_for_filedownload()"},"after":[{"result":{"duration":1000000,"status":"passed"},"match":{"location":"factory.ApplicationHooks.tearDown(io.cucumber.java.Scenario)"}}],"keyword":"Then "}],"tags":[{"name":"@feature"},{"name":"@smoketest"}]}],"name":"Feature to Learning_Automation test functionality","description":"","id":"feature-to-learning-automation-test-functionality","keyword":"Feature","uri":"file:src/test/resources/Features/Learning_Feature/learning.switchto.feature","tags":[{"name":"@feature","type":"Tag","location":{"line":4,"column":1}}]}]